{
    "minId": 100000,
    "maxId": 999999,
    "primaryColor": "#ff6f04",
    "socialLoginProviders": ["Google", "Facebook", "Twitter"],
    "statusOrder": ["waiting", "working", "complete"],
    "defaultPictureProductUrl": "https://firebasestorage.googleapis.com/v0/b/simple-store-fbe1f.appspot.com/o/logo512.png?alt=media&token=1612b11a-beaf-4d9f-843b-a756b566a515",
    "productPictureFolder": "images",
    "currencySign": "₪",
    "productsCollection": "products",
    "categoriesCollection": "categories",
    "ordersCollection": "orders", 
    "clientsCollection": "clients",
    "adminsEmailList": ["admin@tel-ran.co.il"],
    "adminsCollection": "admins"
}